{
  "name": "statements/3287952000.docx",
  "bucket": "ghosh-ele-works.appspot.com",
  "contentType": "application/vnd.openxmlformats-officedocument.wordprocessingml.document",
  "metageneration": 1,
  "generation": 1648736600166,
  "storageClass": "STANDARD",
  "contentDisposition": "inline",
  "cacheControl": "public, max-age=3600",
  "contentEncoding": "identity",
  "downloadTokens": [
    "38d42e3c-ae52-48d4-8efd-3bc88bfc6509"
  ],
  "etag": "ClmF5ol23aoYFCO8/sa7CxIhhwM",
  "timeCreated": "2022-03-31T14:23:20.166Z",
  "updated": "2022-03-31T14:23:20.166Z",
  "size": 62453,
  "md5Hash": "1JLF7y7vpNWt1tTJTmDd7Q==",
  "crc32c": "3724446986"
}